_solib_darwin_x86_64/_U@macos_Uopencv_S_S_Copencv___Uopt_Sopencv@3_Slib/libopencv_calib3d.dylib
_solib_darwin_x86_64/_U@macos_Uopencv_S_S_Copencv___Uopt_Sopencv@3_Slib/libopencv_core.dylib
_solib_darwin_x86_64/_U@macos_Uopencv_S_S_Copencv___Uopt_Sopencv@3_Slib/libopencv_features2d.dylib
_solib_darwin_x86_64/_U@macos_Uopencv_S_S_Copencv___Uopt_Sopencv@3_Slib/libopencv_highgui.dylib
_solib_darwin_x86_64/_U@macos_Uopencv_S_S_Copencv___Uopt_Sopencv@3_Slib/libopencv_imgcodecs.dylib
_solib_darwin_x86_64/_U@macos_Uopencv_S_S_Copencv___Uopt_Sopencv@3_Slib/libopencv_imgproc.dylib
_solib_darwin_x86_64/_U@macos_Uopencv_S_S_Copencv___Uopt_Sopencv@3_Slib/libopencv_video.dylib
_solib_darwin_x86_64/_U@macos_Uopencv_S_S_Copencv___Uopt_Sopencv@3_Slib/libopencv_videoio.dylib
edge_engine-1.0.3.dist-info/METADATA
edge_engine-1.0.3.dist-info/RECORD
edge_engine-1.0.3.dist-info/WHEEL
edge_engine/__init__.py
edgestore/__init__.py
edgestore/protos/devices/optimal_options_pb2.py
edgestore/protos/graph/attr_value_pb2.py
edgestore/protos/graph/graph_pb2.py
edgestore/protos/graph/image_props_pb2.py
edgestore/protos/graph/node_def_pb2.py
edgestore/protos/graph/object_detection_pb2.py
edgestore/protos/graph/op_value_pb2.py
edgestore/protos/graph/ops/node_specs_pb2.py
edgestore/protos/graph/types_pb2.py
edgestore/protos/graph/versions_pb2.py
edgestore/protos/inference_api/primitivies/associated_data_pb2.py
edgestore/protos/inference_api/primitivies/box_pb2.py
edgestore/protos/inference_api/primitivies/detection_class_pb2.py
edgestore/protos/inference_api/primitivies/generic_detection_pb2.py
edgestore/protos/inference_api/primitivies/generic_relational_graph_pb2.py
edgestore/protos/inference_api/primitivies/instance_segmentation_pb2.py
edgestore/protos/inference_api/primitivies/point_pb2.py
edgestore/protos/inference_api/primitivies/proto_tensor_pb2.py
edgestore/protos/inference_api/primitivies/results_pb2.py
edgestore/protos/model_info/global_props_pb2.py
edgestore/protos/model_info/label_map_pb2.py
edgestore/protos/package/model_package_pb2.py
edgestore/python/EdgeModel.py
