Metadata-Version: 2.1
Name: edge_engine
Version: 1.0.3
Requires-Dist: numpy
Requires-Dist: opencv-python
Requires-Dist: protobuf
